{ "chairman":[{
  "name": "Chanaka Wickramasinghe",
  "title": "CHAIRPERSON",
  "linkedin": "https://www.linkedin.com/in/chanakawick/",
  "facebook": "https://www.facebook.com/cwickramasinghe",
  "image": ""
    }
],

"vicechairs": [
    {
    "name": "Hapuarachchige Supun Hansika",
    "title": "VICE CHAIRPERSON",
    "linkedin": "https://www.linkedin.com/in/spoonhansika/",
    "facebook": "https://www.facebook.com/spoonhansika/",
    "image": ""
    },
    {
    "name": "Uvini De Silva",
    "title": "VICE CHAIRPERSON",
    "linkedin": "https://www.linkedin.com/in/uvinidesilva/",
    "facebook": "https://www.facebook.com/UviniDeSilva",
    "image": ""
    },
    {
    "name": "Michelle Fara de Zilva",
    "title": "VICE CHAIRPERSON",
    "linkedin": "http://www.linkedin.com/in/MichelledeZilva",
    "facebook": "https://www.facebook.com/mfdezilva/",
    "image": ""
    }
],

"programteam": [
    {
    "name": "Singhe Silva",
    "title": "PROGRAM TEAM LEAD",
    "linkedin": "https://www.linkedin.com/mwlite/in/singhesilva",
    "facebook": "https://m.facebook.com/100001836527905/",
    "image": ""
    },
    {
    "name": "Himasha Randil Nanayakkara",
    "title": "PROGRAM TEAM MEMBER",
    "linkedin": "https://www.linkedin.com/in/himasha-randil-1650b5216/",
    "facebook": "https://www.facebook.com/himasha.randil.568",
    "image": ""
    },
    {
    "name": "Kavindu Nirmana Weerasinghe",
    "title": "PROGRAM TEAM MEMBER",
    "linkedin": "https://www.linkedin.com/in/nirmana99/",
    "facebook": "https://www.facebook.com/kavindunirmana.weerasinghe.3",
    "image": ""
    },
    {
    "name": "Venudi Dayaratne",
    "title": "PROGRAM TEAM MEMBER",
    "linkedin": "https://www.linkedin.com/in/venudidayaratne",
    "instagram": "https://instagram.com/_venudi_?igshid=YmMyMTA2M2Y=",
    "image": ""
    },
    {
    "name": "Visal Mendis",
    "title": "PROGRAM TEAM MEMBER",
    "linkedin": "https://www.linkedin.com/in/visal-mendis-988919200",
    "facebook": "https://www.facebook.com/profile.php?id=100008705351369",
    "image": ""
    }
],

"secretaryteam": [
    {
    "name": "Senuri Methma Ranatunga",
    "title": "SECRETARY TEAM LEAD",
    "linkedin": "https://www.linkedin.com/in/senuri-ranatunga-85959b207",
    "facebook": "https://www.facebook.com/senuri.ranatunga.98",
    "image": ""
    },
    {
    "name": "Kasuni Dilshani Perera",
    "title": "SECRETARY TEAM MEMBER",
    "linkedin": "http://www.linkedin.com/in/kasuni-dilshani-perera-9b6b521a4",
    "facebook": "https://www.facebook.com/kasuni.perera.31586526",
    "image": ""
    },
    {
    "name": "Pawani Kalegana",
    "title": "SECRETARY TEAM MEMBER",
    "linkedin": "https://www.linkedin.com/in/pawani-kalegana-163992216",
    "instagram": "https://www.instagram.com/pawii_kay/",
    "image": ""
    },
    {
    "name": "Muhammad Suraif",
    "title": "SECRETARY TEAM MEMBER",
    "linkedin": "https://www.linkedin.com/in/muhammad-suraif",
    "facebook": "https://www.facebook.com/suraif.muhamed",
    "image": ""
    },
    {
    "name": "Janani Erandika",
    "title": "SECRETARY TEAM MEMBER",
    "linkedin": "https://www.linkedin.com/in/janani-wijekoon-0792b6199",
    "facebook": "https://www.facebook.com/janu.erandi",
    "image": ""
    }
],

"publicityteam": [
    {
    "name": "Asanka Fernando",
    "title": "PUBLICITY TEAM LEAD",
    "linkedin": "http://www.linkedin.com/in/asanka-fernando",
    "facebook": "https://www.facebook.com/profile.php?id=100006134342150",
    "image": ""
    },
    {
    "name": "Ashinika Nethmini Bandara",
    "title": "PUBLICITY TEAM MEMBER",
    "linkedin": "http://www.linkedin.com/in/nethmini-bandara",
    "facebook": "https://www.facebook.com/ashinika.nethmini/",
    "image": ""
    },
    {
    "name": "Manith Jayaba Marapperuma",
    "title": "PUBLICITY TEAM MEMBER",
    "linkedin": "https://www.linkedin.com/in/manith-marapperuma-686597146/",
    "facebook": "https://www.facebook.com/manithjayaba.marapperuma/",
    "image": ""
    },
    {
    "name": "Pahan Rathnayake",
    "title": "PUBLICITY TEAM MEMBER",
    "linkedin": "https://www.linkedin.com/in/pahan-rathnayake-24a77b167",
    "facebook": "https://www.facebook.com/pahan.rathnayake.7",
    "image": ""
    },
    {
    "name": "Navin Thamindu Chandrasiri",
    "title": "WEBMASTER",
    "linkedin": "https://www.linkedin.com/in/navintc/",
    "facebook": "https://www.facebook.com/navin.thamindu/",
    "image": ""
    },
    {
    "name": "Nalinda Gamaarachchi ",
    "title": "PUBLICITY TEAM MEMBER",
    "linkedin": "https://www.linkedin.com/in/nalindagamaarachchi",
    "image": ""
    }
],

"logisticsteam": [
    {
    "name": "Aamir Waais",
    "title": "LOGISTICS TEAM LEAD",
    "linkedin": "https://www.linkedin.com/in/aamir-waais-723412203",
    "instagram": "https://www.instagram.com/aamirwaais/",
    "image": ""
    },
    {
    "name": "Disara Mapalagama",
    "title": "LOGISTICS TEAM MEMBER",
    "linkedin": "https://www.linkedin.com/mwlite/in/disara-mapalagama-63972121a",
    "facebook": "https://www.facebook.com/disara.mapalagama.5",
    "image": ""
    },
    {
    "name": "Sahan Nimna Ravihansa",
    "title": "LOGISTICS TEAM MEMBER",
    "linkedin": "https://www.linkedin.com/in/sahan-jayasinghe-4b1457215",
    "facebook": "https://www.facebook.com/sahan.jayasinghe.100",
    "image": ""
    },
    {
    "name": "Sanjula Kodithuwakku",
    "title": "LOGISTICS TEAM MEMBER",
    "linkedin": "https://www.linkedin.com/in/sanjula-kodithuwakku27864b19a",
    "facebook": "https://www.facebook.com/nemendi.kodithuwakku.3",
    "image": ""
    },
    {
    "name": "Janindu Abeygunawardhana",
    "title": "LOGISTICS TEAM MEMBER",
    "linkedin": "https://www.linkedin.com/in/dilsara-abeygunawardhana-9b54b0202/",
    "facebook": "https://www.facebook.com/janindu.dilsara/",
    "image": ""
    }
],

"financeteam": [
    {
    "name": "Senal Chandrasekara",
    "title": "FINANCE TEAM LEAD",
    "linkedin": "http://www.linkedin.com/in/senal-chandrasekara-06a9b3197",
    "facebook": "https://www.facebook.com/senal.chandrasekara.16",
    "image": ""
    },
    {
    "name": "Kivi Amarakoon Arachchi",
    "title": "FINANCE TEAM MEMBER",
    "linkedin": "https://www.linkedin.com/in/kivi-amarakoon-543a84195/",
    "facebook": "https://www.facebook.com/profile.php?id=100008353609477",
    "image": ""
    },
    {
    "name": "Milni Wijebandara",
    "title": "FINANCE TEAM MEMBER",
    "instagram": "https://www.instagram.com/mill.icent4",
    "image": ""
    }
],

"designteam": [
    {
    "name": "Chethana Prasadika",
    "title": "DESIGN TEAM LEAD",
    "linkedin": "https://www.linkedin.com/in/chethana-prasadika/",
    "facebook": "https://www.facebook.com/chethana.senarath.5/",
    "image": ""
    },
    {
    "name": "Srimal Fernando",
    "title": "DESIGN TEAM MEMBER",
    "linkedin": "https://www.linkedin.com/in/srimal-online/",
    "facebook": "https://www.facebook.com/srimal.online",
    "image": ""
    },
    {
    "name": "Dilky Liyanage",
    "title": "DESIGN TEAM MEMBER",
    "linkedin": "https://www.linkedin.com/in/dilky-l-b615b0130/",
    "facebook": "https://www.facebook.com/dilky.liyanage.9/",
    "image": ""
    },
    {
    "name": "Bhathusha Thushianthan",
    "title": "DESIGN TEAM MEMBER",
    "linkedin": "https://www.linkedin.com/in/bhathu-thushi",
    "image": ""
    }
]
}
